{
  "rules": [
    {
      "id": "tj-ghunnah",
      "name": "Ghunnah",
      "nameAr": "غنة",
      "color": "#16a34a",
      "defaultColor": "#16a34a",
      "bold": false
    },
    {
      "id": "tj-qalqalah",
      "name": "Qalqalah",
      "nameAr": "قلقة",
      "color": "#0284c7",
      "defaultColor": "#0284c7",
      "bold": false
    },
    {
      "id": "tj-heavy",
      "name": "Heavy Letters",
      "nameAr": "تفخيم",
      "color": "#2057ee",
      "defaultColor": "#1e3a8a",
      "bold": true
    },
    {
      "id": "tj-ra-heavy",
      "name": "Ra Heavy",
      "nameAr": "ر تفخيم",
      "color": "#2c61f2",
      "defaultColor": "#1e3a8a",
      "bold": true
    },
    {
      "id": "tj-ra-light",
      "name": "Ra Light",
      "nameAr": "ر ترقيق",
      "color": "#69d9ec",
      "defaultColor": "#06b6d4",
      "bold": false
    },
    {
      "id": "tj-madd",
      "name": "Madd",
      "nameAr": "مد",
      "color": "#b50d0d",
      "defaultColor": "#dc2626",
      "bold": true,
      "letters": "آ وٓ لَٓ مِّٓۖ يَٰٓ ۦٓ أٓ لَٰٓ ئِ ۥٓ"
    },
    {
      "id": "tj-silent",
      "name": "Silent",
      "nameAr": "ساكن",
      "color": "#9ca3af",
      "defaultColor": "#9ca3af",
      "bold": false
    },
    {
      "id": "tj-special",
      "name": "Special",
      "nameAr": "خاص",
      "color": "#d97706",
      "defaultColor": "#d97706",
      "bold": true
    },
    {
      "id": "tj-custom-1771730096110",
      "name": "Ikhfaa",
      "nameAr": "اخفاء",
      "color": "#a5a1a1",
      "defaultColor": "#a5a1a1",
      "bold": false,
      "type": "custom",
      "letters": "ىٗ",
      "customPositions": []
    }
  ],
  "overrides": [],
  "conditions": {
    "qalqalah": {
      "id": "tj-qalqalah",
      "name": "Qalqalah",
      "nameAr": "قلقة",
      "letters": "قطبجد",
      "triggers": [
        "sukun",
        "shadda",
        "wordEnd"
      ]
    },
    "ghunnah": {
      "id": "tj-ghunnah",
      "name": "Ghunnah",
      "nameAr": "غنة",
      "letters": "نم",
      "triggers": [
        "shadda",
        "noonSakinah",
        "meemSakinah",
        "tanween"
      ]
    },
    "heavy": {
      "id": "tj-heavy",
      "name": "Heavy Letters",
      "nameAr": "تفخيم",
      "letters": "صضطظق",
      "triggers": [
        "always"
      ]
    },
    "raHeavy": {
      "id": "tj-ra-heavy",
      "name": "Ra Heavy",
      "nameAr": "ر تفخيم",
      "letters": "ر",
      "triggers": [
        "fatha",
        "damma",
        "tanweenFathDamm",
        "sukunAfterHeavy"
      ]
    },
    "raLight": {
      "id": "tj-ra-light",
      "name": "Ra Light",
      "nameAr": "ر ترقيق",
      "letters": "ر",
      "triggers": [
        "kasra",
        "tanweenKasr",
        "sukunAfterLight"
      ]
    },
    "madd": {
      "id": "tj-madd",
      "name": "Madd",
      "nameAr": "مد",
      "letters": "آ وٓ لَٓ مِّٓۖ يَٰٓ ۦٓ أٓ لَٰٓ ئِ ۥٓ",
      "triggers": [
        "beforeHamza",
        "beforeSukun"
      ]
    },
    "silent": {
      "id": "tj-silent",
      "name": "Silent",
      "nameAr": "ساكن",
      "letters": "لنم",
      "triggers": [
        "lamShamsiyya",
        "idghamNoGhunnah",
        "idghamWithGhunnah"
      ]
    },
    "special": {
      "id": "tj-special",
      "name": "Special",
      "nameAr": "خاص",
      "letters": "",
      "triggers": []
    }
  },
  "sets": {
    "idghamWithGhunnah": "ينمو",
    "idghamNoGhunnah": "لر",
    "ikhfa": "تثجدذزسشصضطظفقك",
    "lamShamsiyya": "تثدذرزسشصضطظلن",
    "hamzaLetters": "ءأإؤئ"
  }
}